{"chevaux":[{"participation":true,"arrive":1,"numero":"12","cote":2.6,"rapportMin":1.4,"rapportMax":1.7},{"participation":true,"arrive":2,"numero":"14","cote":22.6,"rapportMin":3.9,"rapportMax":6.8},{"participation":true,"arrive":3,"numero":"5","cote":21,"rapportMin":3.3,"rapportMax":5.6},{"participation":true,"arrive":4,"numero":"10","cote":45.7,"rapportMin":4.2,"rapportMax":7.3},{"participation":true,"arrive":5,"numero":"8","cote":174,"rapportMin":17,"rapportMax":31.1},{"participation":true,"arrive":6,"numero":"1","cote":167.8,"rapportMin":14.8,"rapportMax":26.9},{"participation":true,"arrive":7,"numero":"2","cote":6.3,"rapportMin":3.3,"rapportMax":5.6},{"participation":true,"arrive":8,"numero":"3","cote":11.6,"rapportMin":2.2,"rapportMax":3.6},{"participation":true,"arrive":9,"numero":"4","cote":48.8,"rapportMin":6.9,"rapportMax":12.4},{"participation":true,"arrive":10,"numero":"6","cote":21.1,"rapportMin":1.9,"rapportMax":3},{"participation":true,"arrive":11,"numero":"7","cote":84.9,"rapportMin":12.1,"rapportMax":22},{"participation":true,"arrive":12,"numero":"9","cote":6,"rapportMin":1.7,"rapportMax":2.6},{"participation":true,"arrive":13,"numero":"11","cote":52.4,"rapportMin":3.8,"rapportMax":6.6},{"participation":true,"arrive":14,"numero":"13","cote":7,"rapportMin":2.8,"rapportMax":4.7}],"status":"terminé","heure":" 20:47"}