{"chevaux":[{"cote":"226,7","nom":"CAPTAIN LYL","numero":"1","participation":true},{"cote":"29,3","nom":"CINCINNATI BOND","numero":"2","participation":true},{"cote":"153,4","nom":"CAENNAISE","numero":"3","participation":true},{"cote":"20,5","nom":"CASSANDRE D'EM","numero":"4","participation":true},{"cote":"10","nom":"CANDELA","numero":"5","participation":true},{"cote":"18,9","nom":"CAVALLERIA","numero":"6","participation":true},{"cote":"6,7","nom":"CELINA POLKA","numero":"7","participation":true},{"cote":"19,6","nom":"COCKTAIL MESLOIS","numero":"8","participation":true},{"cote":"6,6","nom":"CYPRIEN DES BORDES","numero":"9","participation":true},{"cote":"1,7","nom":"CANADIEN D'AM","numero":"10","participation":true}],"heure":" 13:50","date":"29012017","nom":"R1C1"}