{"chevaux":[{"participation":true,"arrive":1,"numero":"8","cote":2.7,"rapportMin":1.2,"rapportMax":1.4},{"participation":true,"arrive":2,"numero":"10","cote":8.7,"rapportMin":3,"rapportMax":6.3},{"participation":true,"arrive":3,"numero":"1","cote":16.1,"rapportMin":2,"rapportMax":4},{"participation":true,"arrive":4,"numero":"4","cote":10.3,"rapportMin":2.5,"rapportMax":5},{"participation":true,"arrive":5,"numero":"2","cote":30.1,"rapportMin":5.8,"rapportMax":12.6},{"participation":true,"arrive":6,"numero":"3","cote":31.1,"rapportMin":4.9,"rapportMax":10.7},{"participation":true,"arrive":7,"numero":"5","cote":5.9,"rapportMin":1.6,"rapportMax":2.9},{"participation":true,"arrive":8,"numero":"7","cote":6.7,"rapportMin":2,"rapportMax":3.8},{"participation":true,"arrive":9,"numero":"9","cote":7.8,"rapportMin":1.3,"rapportMax":2},{"participation":true,"arrive":10,"numero":"11","cote":104.5,"rapportMin":3.9,"rapportMax":8.4},{"participation":false,"numero":"6"}],"status":"terminé","heure":" 15:25"}