{"chevaux":[{"cote":"71,7","musique":"Da(16)Da1a2aDa7a","nom":"DROTTNING VIKING","numero":"1","participation":true},{"cote":"31,6","musique":"(16)DaDaDa1aDaDa3a1aDa","nom":"DIVA MESLINOISE","numero":"2","participation":true},{"cote":"18,2","musique":"(16)4aDaDa4a1aDa1aDa2a","nom":"DIVINE DE NAVARY","numero":"3","participation":true},{"cote":"46,9","musique":"3a(16)9a3a1a4a4a1a3aDa","nom":"DWELLING HEIGHTS","numero":"4","participation":true},{"cote":"13,8","musique":"2a(16)1aDaDaDa2a2aDaDa","nom":"DULCIA","numero":"5","participation":true},{"nom":"DIVA DE BRION","numero":"6","participation":false},{"cote":"93,9","musique":"Da(16)Da7a5a1a2a5a1a8a","nom":"DIVINE HONEY","numero":"7","participation":true},{"cote":"3,3","musique":"(16)4a9a2a1a1a","nom":"DOTKA DE LOIRON","numero":"8","participation":true},{"cote":"6,2","musique":"7a(16)1a0a1a2aDa","nom":"DIANE D'HAUFOR","numero":"9","participation":true},{"cote":"10,2","musique":"1a1a(16)2a2a1aDaDa","nom":"DENTELLA BELLA","numero":"10","participation":true},{"cote":"36,3","musique":"Da2a(16)1a2a3aDa7m7a7a","nom":"DIVINE CHARENTAISE","numero":"11","participation":true},{"cote":"16,7","musique":"(16)3a1a2a2a1a7mDmDa","nom":"DOLCE VITA D'EM","numero":"12","participation":true},{"cote":"15,8","musique":"3aDa5m5a(16)2mDmDm6mDa","nom":"DORNATIS DU RIB","numero":"13","participation":true},{"cote":"5,4","musique":"(16)1a5aDmDa2aDa1a6a2a","nom":"DANSEUSE DU CITRUS","numero":"14","participation":true},{"cote":"16,2","musique":"2a(16)7a2aDa8aDa9a2a","nom":"DOUBLE CROWN","numero":"15","participation":true}],"date":"24012017","nom":"R2C4"}