{"chevaux":[{"cote":"21,3","musique":"Da3a2a6aDa1aDaDaDaDa","nom":"COME BACK","numero":"1","participation":true},{"cote":"2","musique":"1a1a1aDa0a5aDaDa2a2a","nom":"TITANIUM GAR","numero":"2","participation":true},{"cote":"-","musique":"4a0a1a2aDa5aDa2a7a0a","nom":"GABBYTO","numero":"3","participation":true},{"cote":"-","musique":"4a2a1a1aDa2aDa7a4a2a","nom":"GRIMALDI","numero":"4","participation":true},{"cote":"2,9","musique":"1aAa1a1a1a1a1a1a3a1a","nom":"FUTURE SHADOW","numero":"5","participation":true},{"cote":"-","musique":"3a6aDa5a4a8aDa0aDa7a","nom":"ENJOY LIKEASTAR","numero":"6","participation":true},{"cote":"-","musique":"1a3a4a3a4a6a1a0a4a1a","nom":"HENNA VILLA","numero":"7","participation":true},{"cote":"10,6","musique":"4a0a1a2a4a6a4a0a2a3a","nom":"ECLAT VIVANT","numero":"8","participation":true},{"cote":"21,3","musique":"6a2a8a6a6a7a0a6a4a0a","nom":"VELO D'ANDAIN","numero":"9","participation":true},{"cote":"21,3","musique":"Da6a2a2a0a8a0a2a3a6a","nom":"VIX DE CHANTELOUP","numero":"10","participation":true},{"cote":"21,3","musique":"3a4a5a2a8a8a7a0a5a5a","nom":"MACHO BYD","numero":"11","participation":true},{"cote":"21,3","musique":"Da4a3a6a1a","nom":"BACI LOVE","numero":"12","participation":true}],"date":"24012017","nom":"R3C5"}